ftp_cli/__init__.py
ftp_cli/main.py
ftp_cli/src/__init__.py
ftp_cli/src/config/__init__.py
ftp_cli/src/config/controllers.py
ftp_cli/src/config/schema.py
ftp_cli/src/config/utils.py
ftp_cli/src/ftp.py
ftp_cli/src/models.py
ftp_cli/src/utils.py
ftp_cli-0.3.0.dist-info/entry_points.txt
ftp_cli-0.3.0.dist-info/WHEEL
ftp_cli-0.3.0.dist-info/METADATA
ftp_cli-0.3.0.dist-info/RECORD
